swish/__init__.py
swish/client.py
swish/environment.py
swish/exceptions.py
swish/models.py
tests/__init__.py
tests/cert.pem
tests/key.pem
tests/swish.pem
tests/test_client.py
tests/test_environment.py
swish-1.5.dist-info/LICENSE
swish-1.5.dist-info/METADATA
swish-1.5.dist-info/WHEEL
swish-1.5.dist-info/top_level.txt
swish-1.5.dist-info/RECORD
