Metadata-Version: 2.1
Name: swish
Version: 1.5
Summary: Swish Python Client Library
Home-page: https://github.com/MadSpindel/swish-python
Author: Fredrik Sundqvist
Author-email: fsundqvist@gmail.com
License: MIT
Classifier: Development Status :: 5 - Production/Stable
Classifier: Intended Audience :: Developers
Classifier: Topic :: Software Development :: Libraries :: Python Modules
Classifier: License :: OSI Approved :: MIT License
Classifier: Programming Language :: Python :: 3.8
Classifier: Programming Language :: Python :: 3.9
Classifier: Programming Language :: Python :: 3.10
Classifier: Programming Language :: Python :: 3.11
Classifier: Programming Language :: Python :: 3.12
License-File: LICENSE
Requires-Dist: requests >=2.9.1
Requires-Dist: schematics >=2.0.0.dev2
